histogram/__init__.py
histogram/executor.py
histogram/histogram.py
histogram/utils.py
himpy-0.0.1.dist-info/LICENSE
himpy-0.0.1.dist-info/METADATA
himpy-0.0.1.dist-info/WHEEL
himpy-0.0.1.dist-info/top_level.txt
himpy-0.0.1.dist-info/RECORD
