Metadata-Version: 2.1
Name: himpy
Version: 0.0.1
Summary: Histogram model
Home-page: https://github.com/lshist/histogram
Author: Sergei Papulin
Author-email: papulin.edu@gmail.com
License: UNKNOWN
Project-URL: Bug Tracker, https://github.com/lshist/histogram/issues
Platform: UNKNOWN
Classifier: Programming Language :: Python :: 3
Classifier: License :: OSI Approved :: MIT License
Classifier: Operating System :: OS Independent
Requires-Python: >=3.6
License-File: LICENSE
Requires-Dist: pyparsing (>=2.4)
